{"Title":"Scrubs","Year":"2001–2010","Rated":"TV-14","Released":"02 Oct 2001","Runtime":"22 min","Genre":"Comedy, Drama","Director":"N/A","Writer":"Bill Lawrence","Actors":"Donald Faison, John C. McGinley, Ken Jenkins, Zach Braff","Plot":"In the unreal world of Sacred Heart Hospital, intern John \"J.D\" Dorian learns the ways of medicine, friendship and life.","Language":"English, German, Spanish, American Sign Language","Country":"USA","Awards":"Nominated for 3 Golden Globes. Another 31 wins & 114 nominations.","Poster":"http://ia.media-imdb.com/images/M/MV5BMTc2NjgxMzc5Nl5BMl5BanBnXkFtZTcwOTc0OTM0MQ@@._V1._CR10,44,330,454_SY132_CR3,0,89,132_AL_.jpg_V1_SX300.jpg","Metascore":"N/A","imdbRating":"8.5","imdbVotes":"176,197","imdbID":"tt0285403","Type":"series","Response":"True"}